[{"id":"175364a84def48a4a72d5f694264f7cf9618bf62","error_message":"OK","received_at":"2014-09-29 18:17:14","finished_at":"2014-09-29 18:17:21","js_files":"1","html_files":"1"},{"id":"e0b7a07779f325fffb995a4152e46e9315f2a50b","error_message":"OK","received_at":"2014-09-29 18:16:49","finished_at":"2014-09-29 18:16:57","js_files":"1","html_files":"1"},{"id":"24b08a1c36d787fe0f7a1161d82052a8e256232e","error_message":"OK","received_at":"2014-09-29 18:16:34","finished_at":"2014-09-29 18:16:43","js_files":"1","html_files":"1"},{"id":"3b1d1e33291f2d4505539c4add18c13e164119ed","error_message":"OK","received_at":"2014-09-29 18:16:23","finished_at":"2014-09-29 18:16:31","js_files":"1","html_files":"1"},{"id":"ce582615563c81e3f5b14bc03d97dfdda5012981","error_message":"OK","received_at":"2014-09-29 18:10:22","finished_at":"2014-09-29 18:10:31","js_files":"1","html_files":"1"},{"id":"fcad013d8355d367f4a715de28ba7086c136db88","error_message":"OK","received_at":"2014-09-29 18:08:36","finished_at":"2014-09-29 18:08:43","js_files":"1","html_files":"1"},{"id":"747b0342a429c348690bd7d155aa752e436fe106","error_message":"OK","received_at":"2014-09-29 18:07:24","finished_at":"2014-09-29 18:07:33","js_files":"1","html_files":"1"},{"id":"3fcca1f35e4108a77f19fcf89757c26e2fd73452","error_message":"OK","received_at":"2014-09-29 18:06:27","finished_at":"2014-09-29 18:06:35","js_files":"1","html_files":"1"},{"id":"b76af3746ffb7a023e34cf777ef6fa2759e1ca65","error_message":"OK","received_at":"2014-09-29 18:06:12","finished_at":"2014-09-29 18:06:25","js_files":"1","html_files":"1"},{"id":"3b900affa29daba15b01e073d8548042311a7cb2","error_message":"OK","received_at":"2014-09-29 15:40:32","finished_at":"2014-09-29 15:40:43","js_files":"1","html_files":"1"},{"id":"41a0fffb349a2f9249e876e4315faafa2c38a9a1","error_message":"OK","received_at":"2014-09-29 15:38:13","finished_at":"2014-09-29 15:38:23","js_files":"1","html_files":"1"},{"id":"68f60fa71a0eb660288beb46e72f35b53b043c9f","error_message":"OK","received_at":"2014-09-29 15:30:09","finished_at":"2014-09-29 15:30:18","js_files":"1","html_files":"1"},{"id":"a7094c960399b6c00078c2157a474b8c821519fc","error_message":"OK","received_at":"2014-09-29 15:22:13","finished_at":"2014-09-29 15:22:21","js_files":"1","html_files":"1"},{"id":"de764a40fee5dc6eeada66eed19f68296b20e889","error_message":"OK","received_at":"2014-09-29 15:20:44","finished_at":"2014-09-29 15:20:53","js_files":"1","html_files":"1"},{"id":"86d625dad7ad5e8fa17db0dcab4c8826c265dde3","error_message":"OK","received_at":"2014-09-29 15:18:48","finished_at":"2014-09-29 15:18:55","js_files":"1","html_files":"1"},{"id":"61f7582cb97250480adb2cd833c59bafb3ceb127","error_message":"OK","received_at":"2014-09-29 15:17:30","finished_at":"2014-09-29 15:17:37","js_files":"1","html_files":"1"},{"id":"2cddf91c0f7723f8dde85d09455aff2c8bef6488","error_message":"OK","received_at":"2014-09-29 15:16:22","finished_at":"2014-09-29 15:16:40","js_files":"1","html_files":"1"},{"id":"a6dc97657204c9a098dcf9a364504c64e3933dd3","error_message":"OK","received_at":"2014-09-29 15:12:05","finished_at":"2014-09-29 15:12:16","js_files":"1","html_files":"1"},{"id":"605720dbebb754ae855cb98e1837e4c069802497","error_message":"OK","received_at":"2014-09-29 15:11:11","finished_at":"2014-09-29 15:11:19","js_files":"1","html_files":"1"},{"id":"a3ee1d63f2dd3677644808bf091cc1d3f54b1759","error_message":"OK","received_at":"2014-09-29 15:06:21","finished_at":"2014-09-29 15:06:28","js_files":"1","html_files":"1"},{"id":"e93d3605d6abe945317fb2ebcd64f33c1c61280c","error_message":"OK","received_at":"2014-09-29 15:06:04","finished_at":"2014-09-29 15:06:13","js_files":"1","html_files":"1"},{"id":"a581ce9a12d631529f3284d9d57d1cd2266bdcc5","error_message":"OK","received_at":"2014-09-29 14:46:25","finished_at":"2014-09-29 14:46:33","js_files":"1","html_files":"1"},{"id":"7083d160125d9e24e03f26de3feb15c275c5e370","error_message":"OK","received_at":"2014-09-29 14:44:08","finished_at":"2014-09-29 14:44:17","js_files":"1","html_files":"1"},{"id":"7f3b5eb7c12ef9d9316a21efee4a0319c1f50d2d","error_message":"OK","received_at":"2014-09-29 13:17:41","finished_at":"2014-09-29 13:17:49","js_files":"1","html_files":"1"}]
